mvdef-0.9.4.dist-info/METADATA
mvdef-0.9.4.dist-info/WHEEL
mvdef-0.9.4.dist-info/entry_points.txt
mvdef-0.9.4.dist-info/licenses/LICENSE
mvdef/__init__.py
mvdef/cli.py
mvdef/core/__init__.py
mvdef/core/agenda.py
mvdef/core/check.py
mvdef/core/diff/__init__.py
mvdef/core/diff/diff.py
mvdef/core/manifest/__init__.py
mvdef/core/manifest/all_fmt.py
mvdef/core/manifest/manifest.py
mvdef/core/parse.py
mvdef/core/text_diff.py
mvdef/error_handling/__init__.py
mvdef/error_handling/exceptions.py
mvdef/error_handling/failure.py
mvdef/legacy/__env__.py
mvdef/legacy/__init__.py
mvdef/legacy/__main__.py
mvdef/legacy/agenda_util.py
mvdef/legacy/ast_tokens.py
mvdef/legacy/ast_util.py
mvdef/legacy/backup.py
mvdef/legacy/cli.py
mvdef/legacy/colours.py
mvdef/legacy/def_helpers.py
mvdef/legacy/def_path_util.py
mvdef/legacy/demo.py
mvdef/legacy/deprecations.py
mvdef/legacy/editor.py
mvdef/legacy/editor_util.py
mvdef/legacy/example/__init__.py
mvdef/legacy/example/demo_program.py
mvdef/legacy/example/documentation/demo-success-screenshot-annotated.png
mvdef/legacy/example/new_file.py
mvdef/legacy/example/test/__init__.py
mvdef/legacy/example/test/test_demo.py
mvdef/legacy/import_util.py
mvdef/legacy/io_util.py
mvdef/legacy/traceback_util.py
mvdef/legacy/transfer.py
mvdef/log_utils.py
mvdef/py.typed
mvdef/transfer/__init__.py
mvdef/transfer/base.py
mvdef/transfer/copy.py
mvdef/transfer/list.py
mvdef/transfer/move.py
mvdef/whitespace.py
mvdef-0.9.4.dist-info/RECORD
