Metadata-Version: 2.1
Name: mvdef
Version: 0.9.4
Summary: Package providing command line tools to move/copy function/classes and their associated import statements between files.
Keywords: ast
Author-Email: Louis Maddox <louismmx@gmail.com>
License: MIT
Classifier: Development Status :: 4 - Beta
Classifier: Intended Audience :: Developers
Classifier: Natural Language :: English
Classifier: License :: OSI Approved :: MIT License
Classifier: Operating System :: OS Independent
Classifier: Programming Language :: Python
Classifier: Programming Language :: Python :: Implementation :: CPython
Classifier: Programming Language :: Python :: 3
Classifier: Programming Language :: Python :: 3.10
Classifier: Programming Language :: Python :: 3.11
Project-URL: Documentation, https://mvdef.readthedocs.io/
Project-URL: Homepage, https://github.com/lmmx/fugit
Project-URL: Repository, https://github.com/lmmx/fugit.git
Requires-Python: <3.12,>=3.10
Requires-Dist: argcomplete
Requires-Dist: astor
Requires-Dist: asttokens
Requires-Dist: defopt
Requires-Dist: pyflakes
